ffuzzer.py
ffuzzer-0.1.4.1.dist-info/LICENSE
ffuzzer-0.1.4.1.dist-info/METADATA
ffuzzer-0.1.4.1.dist-info/WHEEL
ffuzzer-0.1.4.1.dist-info/entry_points.txt
ffuzzer-0.1.4.1.dist-info/top_level.txt
ffuzzer-0.1.4.1.dist-info/RECORD
